pyspectra/__init__.py
pyspectra/readers/__init__.py
pyspectra/readers/read_dx.py
pyspectra/readers/read_spc.py
pyspectra/transformers/__init__.py
pyspectra/transformers/spectral_correction.py
pyspectra-0.0.1.2.dist-info/LICENSE
pyspectra-0.0.1.2.dist-info/METADATA
pyspectra-0.0.1.2.dist-info/WHEEL
pyspectra-0.0.1.2.dist-info/top_level.txt
pyspectra-0.0.1.2.dist-info/RECORD
