Metadata-Version: 2.1
Name: pyspectra
Version: 0.0.1.2
Summary: A  python package designed to work with spectroscopy data
Home-page: https://github.com/OEUM/PySpectra
Author: Oscar Ureña
Author-email: oscar.enrique.urena@gmail.com
License: UNKNOWN
Keywords: spectroscopy,nir,ftir,raman,spc,dx,foss,viavi,grams
Platform: UNKNOWN
Classifier: Programming Language :: Python :: 3
Classifier: License :: OSI Approved :: MIT License
Classifier: Operating System :: OS Independent
Requires-Python: >=3.6
Requires-Dist: numpy
Requires-Dist: pandas
Requires-Dist: spc-spectra
Requires-Dist: scipy
